cnn_feature_extractor/__init__.py
cnn_feature_extractor/extractors/__init__.py
cnn_feature_extractor/extractors/cnn_extractor.py
cnn_feature_extractor/models/__init__.py
cnn_feature_extractor/models/classifiers.py
cnn_feature_extractor/models/cnn_packages.py
cnn_feature_extractor/utils/__init__.py
cnn_feature_extractor/utils/dataset.py
cnn_feature_extractor/utils/metrics.py
cnn_feature_extractor/utils/transforms.py
cnn_feature_extractor-0.2.0.dist-info/METADATA
cnn_feature_extractor-0.2.0.dist-info/WHEEL
cnn_feature_extractor-0.2.0.dist-info/top_level.txt
cnn_feature_extractor-0.2.0.dist-info/RECORD
