Metadata-Version: 2.1
Name: cnn_feature_extractor
Version: 0.2.0
Summary: Automatic CNN feature extraction and ML model comparison
Home-page: https://github.com/ituperceptron/cnn_feature_extractor
Author: ITU Perceptron
Author-email: ituperceptron@gmail.com
Classifier: Development Status :: 3 - Alpha
Classifier: Intended Audience :: Science/Research
Classifier: License :: OSI Approved :: MIT License
Classifier: Operating System :: OS Independent
Classifier: Programming Language :: Python :: 3
Classifier: Programming Language :: Python :: 3.7
Classifier: Programming Language :: Python :: 3.8
Classifier: Programming Language :: Python :: 3.9
Classifier: Topic :: Scientific/Engineering :: Artificial Intelligence
Requires-Python: >=3.7
Requires-Dist: torch>=1.9.0
Requires-Dist: torchvision>=0.10.0
Requires-Dist: scikit-learn>=0.24.2
Requires-Dist: numpy>=1.19.2
Requires-Dist: pandas>=1.2.0
Requires-Dist: tqdm>=4.50.0
Requires-Dist: pillow>=8.0.0
Requires-Dist: xgboost>=1.4.0
Requires-Dist: lightgbm>=3.2.0
